mhi/enerplot/Enerplot_AL_doc.chm
mhi/enerplot/__init__.py
mhi/enerplot/__main__.py
mhi/enerplot/annotation.py
mhi/enerplot/application.py
mhi/enerplot/book.py
mhi/enerplot/buildtime.py
mhi/enerplot/command.py
mhi/enerplot/component.py
mhi/enerplot/datafile.py
mhi/enerplot/graph.py
mhi/enerplot/math.py
mhi/enerplot/progress.py
mhi/enerplot/py.typed
mhi/enerplot/remote.py
mhi/enerplot/trace.py
mhi_enerplot-3.0.0.dist-info/LICENSE
mhi_enerplot-3.0.0.dist-info/METADATA
mhi_enerplot-3.0.0.dist-info/WHEEL
mhi_enerplot-3.0.0.dist-info/top_level.txt
mhi_enerplot-3.0.0.dist-info/RECORD
