Metadata-Version: 2.1
Name: mhi-enerplot
Version: 3.0.0
Summary: Manitoba Hydro International: Enerplot Automation library
Author-email: "Manitoba Hydro International Ltd." <pscad@mhi.ca>
License: BSD-3-Clause-Clear
Classifier: Development Status :: 5 - Production/Stable
Classifier: Programming Language :: Python :: 3
Classifier: Programming Language :: Python :: 3.7
Classifier: Programming Language :: Python :: 3.8
Classifier: Programming Language :: Python :: 3.9
Classifier: Programming Language :: Python :: 3.10
Classifier: Programming Language :: Python :: 3.11
Classifier: Programming Language :: Python :: 3.12
Classifier: Programming Language :: Python :: 3.13
Classifier: License :: OSI Approved :: BSD License
Classifier: Operating System :: Microsoft :: Windows
Requires-Python: >=3.7
License-File: LICENSE
Requires-Dist: mhi.common<4,>=3.1.0
Provides-Extra: dev
Requires-Dist: coverage>=7.4.3; extra == "dev"
Requires-Dist: pytest>=8.0.1; extra == "dev"
Requires-Dist: pylint-gitlab>=2.0.0; extra == "dev"
